dcd/__init__.py
dcd/config.py
dcd/core.py
dcd/data.py
dcd/dataclasses.py
dcd/exceptions.py
dcd/py.typed
dcd/types.py
dcd-2.0b1.dist-info/LICENSE
dcd-2.0b1.dist-info/METADATA
dcd-2.0b1.dist-info/WHEEL
dcd-2.0b1.dist-info/top_level.txt
dcd-2.0b1.dist-info/RECORD
