Metadata-Version: 2.1
Name: dcd
Version: 2.0b1
Summary: Simple creation of data classes from dictionaries (fork of dacite).
Home-page: https://github.com/idanmiara/dcd
Author: Konrad Hałas
Author-email: halas.konrad@gmail.com
Maintainer: Idan Miara
Maintainer-email: idan@miara.com
License: MIT
Keywords: dataclasses
Classifier: Development Status :: 5 - Production/Stable
Classifier: Intended Audience :: Developers
Classifier: License :: OSI Approved :: MIT License
Classifier: Operating System :: OS Independent
Classifier: Programming Language :: Python
Classifier: Programming Language :: Python :: 3.7
Classifier: Programming Language :: Python :: 3.8
Classifier: Programming Language :: Python :: 3.9
Classifier: Programming Language :: Python :: 3.10
Classifier: Programming Language :: Python :: 3.11
Classifier: Topic :: Software Development :: Libraries :: Python Modules
Requires-Python: >=3.7
License-File: LICENSE
Provides-Extra: dev
Requires-Dist: pytest (>=5) ; extra == 'dev'
Requires-Dist: pytest-cov ; extra == 'dev'
Requires-Dist: coveralls ; extra == 'dev'
Requires-Dist: black ; extra == 'dev'
Requires-Dist: mypy ; extra == 'dev'
Requires-Dist: pylint ; extra == 'dev'
Requires-Dist: numpy (>=1.21.0) ; extra == 'dev'
